{"v":3,"stories":{"home--page":{"id":"home--page","title":"Home","name":"Page","importPath":"./src/pages/home.stories.mdx"},"lista-de-ícones--page":{"id":"lista-de-ícones--page","title":"Lista de Ícones","name":"Page","importPath":"./src/pages/icon-list.stories.mdx"},"tokens-colors--page":{"id":"tokens-colors--page","title":"Tokens/Colors","name":"Page","importPath":"./src/pages/tokens/colors.stories.mdx"},"tokens-font-sizes--page":{"id":"tokens-font-sizes--page","title":"Tokens/Font Sizes","name":"Page","importPath":"./src/pages/tokens/font-sizes.stories.mdx"},"tokens-font-weights--page":{"id":"tokens-font-weights--page","title":"Tokens/Font Weights","name":"Page","importPath":"./src/pages/tokens/font-weights.stories.mdx"},"tokens-font-families--page":{"id":"tokens-font-families--page","title":"Tokens/Font Families","name":"Page","importPath":"./src/pages/tokens/fonts.stories.mdx"},"tokens-line-heights--page":{"id":"tokens-line-heights--page","title":"Tokens/Line Heights","name":"Page","importPath":"./src/pages/tokens/line-heights.stories.mdx"},"tokens-padding-vertical--page":{"id":"tokens-padding-vertical--page","title":"Tokens/Padding Vertical","name":"Page","importPath":"./src/pages/tokens/py.stories.mdx"},"tokens-radii--page":{"id":"tokens-radii--page","title":"Tokens/Radii","name":"Page","importPath":"./src/pages/tokens/radii.stories.mdx"},"components-button--default":{"id":"components-button--default","title":"Components/Button","name":"Default","importPath":"./src/stories/button.stories.tsx"},"components-button--big-size":{"id":"components-button--big-size","title":"Components/Button","name":"Big Size","importPath":"./src/stories/button.stories.tsx"},"components-button--small-size":{"id":"components-button--small-size","title":"Components/Button","name":"Small Size","importPath":"./src/stories/button.stories.tsx"},"components-button--smaller-size":{"id":"components-button--smaller-size","title":"Components/Button","name":"Smaller Size","importPath":"./src/stories/button.stories.tsx"},"components-button--responsive":{"id":"components-button--responsive","title":"Components/Button","name":"Responsive","importPath":"./src/stories/button.stories.tsx"},"components-button--text-icon":{"id":"components-button--text-icon","title":"Components/Button","name":"Text Icon","importPath":"./src/stories/button.stories.tsx"},"components-button--icon":{"id":"components-button--icon","title":"Components/Button","name":"Icon","importPath":"./src/stories/button.stories.tsx"},"components-button--outline":{"id":"components-button--outline","title":"Components/Button","name":"Outline","importPath":"./src/stories/button.stories.tsx"},"components-button--ghost":{"id":"components-button--ghost","title":"Components/Button","name":"Ghost","importPath":"./src/stories/button.stories.tsx"},"components-card--default":{"id":"components-card--default","title":"Components/Card","name":"Default","importPath":"./src/stories/card.stories.tsx"},"components-formrow--primary":{"id":"components-formrow--primary","title":"Components/FormRow","name":"Primary","importPath":"./src/stories/form-row.stories.tsx"},"components-form--primary":{"id":"components-form--primary","title":"Components/Form","name":"Primary","importPath":"./src/stories/form.stories.tsx"},"components-icon--primary":{"id":"components-icon--primary","title":"Components/Icon","name":"Primary","importPath":"./src/stories/icon.stories.tsx"},"components-navbar--default":{"id":"components-navbar--default","title":"Components/Navbar","name":"Default","importPath":"./src/stories/navbar.stories.tsx"},"components-table--primary":{"id":"components-table--primary","title":"Components/Table","name":"Primary","importPath":"./src/stories/table.stories.tsx"},"components-textinput--default":{"id":"components-textinput--default","title":"Components/TextInput","name":"Default","importPath":"./src/stories/text-input.stories.tsx"},"components-textinput--with-icon":{"id":"components-textinput--with-icon","title":"Components/TextInput","name":"With Icon","importPath":"./src/stories/text-input.stories.tsx"},"components-text--default":{"id":"components-text--default","title":"Components/Text","name":"Default","importPath":"./src/stories/text.stories.tsx"},"components-text--size-12":{"id":"components-text--size-12","title":"Components/Text","name":"Size 12","importPath":"./src/stories/text.stories.tsx"},"components-text--size-20":{"id":"components-text--size-20","title":"Components/Text","name":"Size 20","importPath":"./src/stories/text.stories.tsx"},"components-text--bold":{"id":"components-text--bold","title":"Components/Text","name":"Bold","importPath":"./src/stories/text.stories.tsx"},"components-text--heading":{"id":"components-text--heading","title":"Components/Text","name":"Heading","importPath":"./src/stories/text.stories.tsx"},"components-toast--primary":{"id":"components-toast--primary","title":"Components/Toast","name":"Primary","importPath":"./src/stories/toast.stories.tsx"}}}
